brkbart/__init__.py
brkbart/config.py
brkbart/utils.py
brkbart/scripts/__init__.py
brkbart/scripts/brkbart.py
brkbart-0.0.3.dist-info/LICENSE
brkbart-0.0.3.dist-info/METADATA
brkbart-0.0.3.dist-info/WHEEL
brkbart-0.0.3.dist-info/entry_points.txt
brkbart-0.0.3.dist-info/top_level.txt
brkbart-0.0.3.dist-info/RECORD
