Metadata-Version: 2.1
Name: brkbart
Version: 0.0.3
Summary: Bart-tool wrapping for Bruker PvDataset
Home-page: https://github.com/dvm-shlee/brkbart
Author: SungHo Lee
Author-email: shlee@unc.edu
License: GNLv3
Keywords: bruker bart reconstruction mri
Platform: UNKNOWN
Classifier: Development Status :: 3 - Alpha
Classifier: Intended Audience :: Science/Research
Classifier: Topic :: Scientific/Engineering :: Medical Science Apps.
Classifier: Natural Language :: English
Classifier: Programming Language :: Python :: 3
Requires-Python: >3.5
Requires-Dist: brkraw (>=0.3.8-rc1)
Requires-Dist: paralexe (>=0.1.0)
Requires-Dist: numpy (>=1.19.0)
Requires-Dist: scipy (>=1.6.0)
Requires-Dist: tqdm (>=4.40.0)
